mpiutils/__init__.py
mpiutils/dispatcher.py
mpiutils/mpi_logging.py
mpiutils/mpimap.py
mpiutils-0.1.1.dist-info/DESCRIPTION.rst
mpiutils-0.1.1.dist-info/METADATA
mpiutils-0.1.1.dist-info/RECORD
mpiutils-0.1.1.dist-info/WHEEL
mpiutils-0.1.1.dist-info/entry_points.txt
mpiutils-0.1.1.dist-info/metadata.json
mpiutils-0.1.1.dist-info/top_level.txt
