Metadata-Version: 2.0
Name: mpiutils
Version: 0.1.1
Summary: MPI Utilities
Home-page: UNKNOWN
Author: Ben Kaehler
Author-email: benjamin.kaehler@anu.edu.au
License: GPLv3 or any later version
Keywords: parallel,workflow,MPI
Platform: any
Requires-Dist: click
Provides-Extra: mpi
Requires-Dist: mpi4py; extra == 'mpi'
